LICENSE
MANIFEST.in
README.rst
setup.cfg
setup.py
docs/Makefile
docs/make.bat
docs/source/conf.py
docs/source/gnosis.eth.clients.rst
docs/source/gnosis.eth.contracts.rst
docs/source/gnosis.eth.django.rst
docs/source/gnosis.eth.eip712.rst
docs/source/gnosis.eth.oracles.abis.rst
docs/source/gnosis.eth.oracles.rst
docs/source/gnosis.eth.rst
docs/source/gnosis.rst
docs/source/gnosis.safe.rst
docs/source/index.rst
docs/source/modules.rst
docs/source/quickstart.rst
fs_attestation_safe_eth_py.egg-info/PKG-INFO
fs_attestation_safe_eth_py.egg-info/SOURCES.txt
fs_attestation_safe_eth_py.egg-info/dependency_links.txt
fs_attestation_safe_eth_py.egg-info/requires.txt
fs_attestation_safe_eth_py.egg-info/top_level.txt
gnosis/__init__.py
gnosis/py.typed
gnosis/cowsap/__init__.py
gnosis/cowsap/cow_swap_api.py
gnosis/cowsap/order.py
gnosis/cowsap/tests/__init__.py
gnosis/cowsap/tests/test_cow_swap_api.py
gnosis/eth/__init__.py
gnosis/eth/constants.py
gnosis/eth/ethereum_client.py
gnosis/eth/ethereum_network.py
gnosis/eth/exceptions.py
gnosis/eth/multicall.py
gnosis/eth/typing.py
gnosis/eth/utils.py
gnosis/eth/account_abstraction/__init__.py
gnosis/eth/account_abstraction/bundler_client.py
gnosis/eth/account_abstraction/constants.py
gnosis/eth/account_abstraction/exceptions.py
gnosis/eth/account_abstraction/user_operation.py
gnosis/eth/account_abstraction/user_operation_receipt.py
gnosis/eth/clients/__init__.py
gnosis/eth/clients/blockscout_client.py
gnosis/eth/clients/contract_metadata.py
gnosis/eth/clients/ens_client.py
gnosis/eth/clients/etherscan_client.py
gnosis/eth/clients/sourcify_client.py
gnosis/eth/contracts/__init__.py
gnosis/eth/contracts/contract_base.py
gnosis/eth/contracts/abis/CPKFactory.json
gnosis/eth/contracts/abis/CompatibilityFallbackHandler_V1_3_0.json
gnosis/eth/contracts/abis/CompatibilityFallbackHandler_V1_4_1.json
gnosis/eth/contracts/abis/DelegateConstructorProxy.json
gnosis/eth/contracts/abis/ERC1155.json
gnosis/eth/contracts/abis/ERC20.json
gnosis/eth/contracts/abis/ERC20TestToken.json
gnosis/eth/contracts/abis/ERC721.json
gnosis/eth/contracts/abis/GnosisSafe_V0_0_1.json
gnosis/eth/contracts/abis/GnosisSafe_V1_0_0.json
gnosis/eth/contracts/abis/GnosisSafe_V1_1_1.json
