Metadata-Version: 2.1
Name: fs-attestation-safe-eth-py
Version: 1.0.0
Summary: Modified Safe Ecosystem Foundation utilities for Ethereum projects and FailSafe Attestation Service
Home-page: https://github.com/safe-global/safe-eth-py
Author: Mohan
Author-email: mohan@ethlas.com
License: MIT License
Project-URL: Documentation, https://safe-eth-py.readthedocs.io/en/latest/
Project-URL: Source, https://github.com/safe-global/safe-eth-py
Project-URL: Tracker, https://github.com/safe-global/safe-eth-py/issues
Keywords: ethereum,web3,django,safe,cowswap,gnosis
Classifier: Environment :: Web Environment
Classifier: Framework :: Django
Classifier: Framework :: Django :: 2.0
Classifier: Framework :: Django :: 3.0
Classifier: Framework :: Django :: 4.0
Classifier: Intended Audience :: Developers
Classifier: License :: OSI Approved :: MIT License
Classifier: Operating System :: OS Independent
Classifier: Programming Language :: Python
Classifier: Programming Language :: Python :: 3.9
Classifier: Programming Language :: Python :: 3.10
Classifier: Programming Language :: Python :: 3.11
Classifier: Programming Language :: Python :: 3.12
Classifier: Topic :: Internet :: WWW/HTTP
Classifier: Topic :: Internet :: WWW/HTTP :: Dynamic Content
Requires-Python: >=3.9
Provides-Extra: django
License-File: LICENSE
